wtf_div/__init__.py
wtf_div/div.py
wtf_div-0.2.0.dist-info/METADATA
wtf_div-0.2.0.dist-info/WHEEL
wtf_div-0.2.0.dist-info/entry_points.txt
wtf_div-0.2.0.dist-info/top_level.txt
wtf_div-0.2.0.dist-info/RECORD
